resomapper/__init__.py
resomapper/auto.py
resomapper/cli.py
resomapper/core/__init__.py
resomapper/core/misc.py
resomapper/core/utils.py
resomapper/format_conversion/DICOM_conversion.py
resomapper/format_conversion/MRS_conversion.py
resomapper/format_conversion/__init__.py
resomapper/format_conversion/bruker_conversion.py
resomapper/model_fitting/DTIfit.py
resomapper/model_fitting/MTRfit.py
resomapper/model_fitting/Tmapfit.py
resomapper/model_fitting/__init__.py
resomapper/processing/__init__.py
resomapper/processing/heatmap.py
resomapper/processing/masking.py
resomapper/processing/preprocessing.py
resomapper/processing/processing.py
resomapper/standalonetools.py
resomapper-1.0.0.dist-info/METADATA
resomapper-1.0.0.dist-info/WHEEL
resomapper-1.0.0.dist-info/entry_points.txt
resomapper-1.0.0.dist-info/licenses/LICENSE
resomapper-1.0.0.dist-info/RECORD
