Metadata-Version: 2.4
Name: resomapper
Version: 1.0.0
Summary: Pipeline for processing MR images and generating parametric maps.
License: MIT
License-File: LICENSE
Author: Biomedical-MR
Requires-Python: >=3.10,<4.0
Classifier: License :: OSI Approved :: MIT License
Classifier: Programming Language :: Python :: 3
Classifier: Programming Language :: Python :: 3.10
Classifier: Programming Language :: Python :: 3.11
Classifier: Programming Language :: Python :: 3.12
Classifier: Programming Language :: Python :: 3.13
Classifier: Programming Language :: Python :: 3.14
Requires-Dist: brkraw (==0.3.11)
Requires-Dist: colorama (>=0.4.6,<0.5.0)
Requires-Dist: dipy (==1.8.0)
Requires-Dist: matplotlib (>=3.10.7,<4.0.0)
Requires-Dist: nibabel (==5.3.2)
Requires-Dist: numpy (==1.26.4)
Requires-Dist: opencv-python (==4.11.0.86)
Requires-Dist: pydicom (==3.0.1)
Requires-Dist: scikit-image (==0.25.2)
Requires-Dist: scikit-learn (==1.6.1)
Requires-Dist: seaborn (>=0.13.2,<0.14.0)
Requires-Dist: simpleitk (==2.4.1)
Requires-Dist: tqdm (>=4.67.1,<5.0.0)
